je_assert_lib/__init__.py
je_assert_lib/assert_lib/__init__.py
je_assert_lib/assert_lib/detail_assert/__init__.py
je_assert_lib/assert_lib/detail_assert/assert_file/__init__.py
je_assert_lib/assert_lib/detail_assert/assert_file/assert_file.py
je_assert_lib/assert_lib/detail_assert/assert_file/assert_file_os.py
je_assert_lib/assert_lib/detail_assert/assert_file/assert_file_pathlib.py
je_assert_lib/assert_lib/detail_assert/assert_str/__init__.py
je_assert_lib/assert_lib/detail_assert/assert_str/contain.py
je_assert_lib/assert_lib/detail_assert/assert_str/special_rule.py
je_assert_lib/assert_lib/detail_assert/assert_str/start_end_with.py
je_assert_lib/assert_lib/genernal_assert/__init__.py
je_assert_lib/assert_lib/genernal_assert/assert_boolean/__init__.py
je_assert_lib/assert_lib/genernal_assert/assert_boolean/assert_boolean_basic.py
je_assert_lib/assert_lib/genernal_assert/assert_class/__init__.py
je_assert_lib/assert_lib/genernal_assert/assert_class/assert_class_basic.py
je_assert_lib/assert_lib/genernal_assert/assert_collections/__init__.py
je_assert_lib/assert_lib/genernal_assert/assert_collections/assert_collections.py
je_assert_lib/assert_lib/genernal_assert/assert_collections/assert_collections_abc.py
je_assert_lib/assert_lib/genernal_assert/assert_collections/assert_collections_basic.py
je_assert_lib/assert_lib/genernal_assert/assert_compare/__init__.py
je_assert_lib/assert_lib/genernal_assert/assert_compare/assert_compare_basic.py
je_assert_lib/assert_lib/genernal_assert/assert_exception/__init__.py
je_assert_lib/assert_lib/genernal_assert/assert_exception/assert_exception_basic.py
je_assert_lib/assert_lib/genernal_assert/assert_weakref/__init__.py
je_assert_lib/assert_lib/genernal_assert/assert_weakref/assert_weak_ref.py
je_assert_lib/assert_lib/genernal_assert/types/__init__.py
je_assert_lib/assert_lib/genernal_assert/types/assert_collection_bultin.py
je_assert_lib/assert_lib/genernal_assert/types/assert_normal_type_bultin.py
je_assert_lib-0.0.1.dist-info/LICENSE
je_assert_lib-0.0.1.dist-info/METADATA
je_assert_lib-0.0.1.dist-info/WHEEL
je_assert_lib-0.0.1.dist-info/top_level.txt
je_assert_lib-0.0.1.dist-info/RECORD
