Metadata-Version: 2.1
Name: je-assert-lib
Version: 0.0.1
Summary: Assert lib to assert everything
Author-email: JE-Chen <zenmailman@gmail.com>
License: MIT
Project-URL: Homepage, https://github.com/JeffreyChen-s-Utils/AssertLib
Classifier: Programming Language :: Python :: 3.7
Classifier: Development Status :: 2 - Pre-Alpha
Classifier: Environment :: Win32 (MS Windows)
Classifier: Environment :: MacOS X
Classifier: Environment :: X11 Applications
Classifier: License :: OSI Approved :: MIT License
Classifier: Operating System :: OS Independent
Requires-Python: >=3.7
License-File: LICENSE
